{"unit":{"title":"Web Design courses","raw_title":"{} courses","source_objects":[{"title":"Web Design","id":6,"description":null,"type":"subcategory","url":"/courses/design/web-design/"}],"item_type":"course","items":[{"_class":"course","id":287012,"title":"Aprende las bases del Css","url":"/course/curso-basico-de-css/","is_paid":false,"visible_instructors":[{"title":"media solutions","name":"media","job_title":"tecnologo en sistemas","image_50x50":"https://img-c.udemycdn.com/user/50x50/2596270_80c8_2.jpg","image_100x100":"https://img-c.udemycdn.com/user/100x100/2596270_80c8_2.jpg","url":"/user/oscargomez5/","display_name":"media solutions","id":2596270,"initials":"MS","_class":"user"}],"image_125_H":"https://img-c.udemycdn.com/course/125_H/287012_a0bf_4.jpg","image_240x135":"https://img-c.udemycdn.com/course/240x135/287012_a0bf_4.jpg","is_practice_test_course":false,"image_480x270":"https://img-c.udemycdn.com/course/480x270/287012_a0bf_4.jpg","published_title":"curso-basico-de-css","tracking_id":"1PKW29uERmC9PijqJuzPgw","headline":"Aprende las bases del css en la web, de esta manera entenderás aun mejor las nuevas tendencias web por venir.","num_subscribers":17249,"caption_locales":[{"_class":"locale","locale":"es_CO","title":"Español (Colombia)","english_title":"Spanish (Colombia)"}],"avg_rating":4.8076925,"avg_rating_recent":4.8101296,"rating":4.8101296,"num_reviews":338,"is_wishlisted":false,"num_published_lectures":43,"num_published_practice_tests":0,"image_50x50":"https://img-c.udemycdn.com/course/50x50/287012_a0bf_4.jpg","image_100x100":"https://img-c.udemycdn.com/course/100x100/287012_a0bf_4.jpg","image_304x171":"https://img-c.udemycdn.com/course/304x171/287012_a0bf_4.jpg","image_750x422":"https://img-c.udemycdn.com/course/750x422/287012_a0bf_4.jpg","is_in_user_subscription":false,"locale":{"title":"Español (Colombia)","simple_english_title":"Spanish","_class":"locale","locale":"es_CO","english_title":"Spanish (Colombia)"},"has_closed_caption":true,"caption_languages":["Español [automático]"],"created":"2014-08-24T16:25:21Z","instructional_level":"Beginner Level","instructional_level_simple":"Beginner","content_length_practice_test_questions":0,"is_user_subscribed":false,"buyable_object_type":"course","published_time":"2014-08-31T23:47:45Z","objectives_summary":["aprender bases del css","Al final del curso, tendras la capacidad de comprender las distintas propiedades del css","Podrás comprender la forma en como se controla la apariencia en las paginas web "],"is_recently_published":false,"last_update_date":"2014-08-31","preview_url":"/course/287012/preview/","learn_url":"/course/curso-basico-de-css/learn/","predictive_score":null,"relevancy_score":null,"input_features":null,"lecture_search_result":null,"curriculum_lectures":[],"order_in_results":null,"curriculum_items":[],"instructor_name":null,"content_info":"8 total hours","content_info_short":"8 hours","bestseller_badge_content":null,"badges":[],"free_course_subscribe_url":"/course/subscribe/?courseId=287012","context_info":{"category":{"title":"Design","tracking_object_type":"cat","url":"/courses/design/","id":269},"label":{"title":"CSS","tracking_object_type":"cl","topic_channel_url":"/topic/css/","url":"/topic/css/","display_name":"CSS","id":5306},"subcategory":null}},{"_class":"course","id":2487362,"title":"Responsive Design ile Tüm Cihazlara Uyumlu Web Siteleri","url":"/course/responsive-design-ile-tum-cihazlara-uyumlu-web-siteleri/","is_paid":false,"visible_instructors":[{"title":"Hakan Çamoğlu","name":"Hakan","id":579524,"image_50x50":"https://img-c.udemycdn.com/user/50x50/579524_144b_3.jpg","image_100x100":"https://img-c.udemycdn.com/user/100x100/579524_144b_3.jpg","url":"/user/hakancamoglu/","display_name":"Hakan Çamoğlu","job_title":"Web Tasarımcısı ve Eğitmen","initials":"HC","_class":"user"},{"title":"Vidobu Eğitim","name":"Vidobu","id":57828388,"image_50x50":"https://img-c.udemycdn.com/user/50x50/57828388_29af.jpg","image_100x100":"https://img-c.udemycdn.com/user/100x100/57828388_29af.jpg","url":"/user/vidobu/","display_name":"Vidobu Eğitim","job_title":"Online Video Eğitim Kütüphanesi","initials":"VE","_class":"user"}],"image_125_H":"https://img-c.udemycdn.com/course/125_H/2487362_af69.jpg","image_240x135":"https://img-c.udemycdn.com/course/240x135/2487362_af69.jpg","is_practice_test_course":false,"image_480x270":"https://img-c.udemycdn.com/course/480x270/2487362_af69.jpg","published_title":"responsive-design-ile-tum-cihazlara-uyumlu-web-siteleri","tracking_id":"lhSkQ_QTRHuI6C89DjGz_A","headline":"Responsive Design ile tüm cihazlara uyumlu web siteleri hazırlamayı öğrenin.","num_subscribers":11881,"caption_locales":[],"avg_rating":4.7708335,"avg_rating_recent":4.796487,"rating":4.796487,"num_reviews":327,"is_wishlisted":false,"num_published_lectures":21,"num_published_practice_tests":0,"image_50x50":"https://img-c.udemycdn.com/course/50x50/2487362_af69.jpg","image_100x100":"https://img-c.udemycdn.com/course/100x100/2487362_af69.jpg","image_304x171":"https://img-c.udemycdn.com/course/304x171/2487362_af69.jpg","image_750x422":"https://img-c.udemycdn.com/course/750x422/2487362_af69.jpg","is_in_user_subscription":false,"locale":{"title":"Türkçe","simple_english_title":"Turkish","english_title":"Turkish","locale":"tr_TR","_class":"locale"},"has_closed_caption":false,"caption_languages":[],"created":"2019-07-31T18:37:40Z","instructional_level":"All Levels","instructional_level_simple":"All Levels","content_length_practice_test_questions":0,"is_user_subscribed":false,"buyable_object_type":"course","published_time":"2019-08-01T12:54:46Z","objectives_summary":["Responsive Tasarım Nedir?","Responsive Tasarım ile tüm cihazlara web sitesi nasıl yapılır?","Responsive Frameworkler"],"is_recently_published":false,"last_update_date":"2019-08-04","preview_url":"/course/2487362/preview/","learn_url":"/course/responsive-design-ile-tum-cihazlara-uyumlu-web-siteleri/learn/","predictive_score":null,"relevancy_score":null,"input_features":null,"lecture_search_result":null,"curriculum_lectures":[],"order_in_results":null,"curriculum_items":[],"instructor_name":null,"content_info":"1 total hour","content_info_short":"1 hour","bestseller_badge_content":null,"badges":[],"free_course_subscribe_url":"/course/subscribe/?courseId=2487362","context_info":{"category":{"title":"Design","tracking_object_type":"cat","id":269,"url":"/courses/design/"},"label":{"title":"Web Design","tracking_object_type":"cl","topic_channel_url":"/topic/web-design/","url":"/topic/web-design/","display_name":"Web Design","id":8320},"subcategory":null}},{"_class":"course","id":2360832,"title":"Curso de Google Sites: Crea tu Sitio Web en Minutos","url":"/course/miwebcongoogle/","is_paid":false,"visible_instructors":[{"title":"Jose Enrique Añazgo","name":"Jose Enrique","id":71671610,"image_50x50":"https://img-c.udemycdn.com/user/50x50/71671610_b5bc_4.jpg","image_100x100":"https://img-c.udemycdn.com/user/100x100/71671610_b5bc_4.jpg","url":"/user/joseaf/","display_name":"Jose Enrique Añazgo","job_title":"Emprendedor Digital","initials":"JA","_class":"user"}],"image_125_H":"https://img-c.udemycdn.com/course/125_H/2360832_8f63_3.jpg","image_240x135":"https://img-c.udemycdn.com/course/240x135/2360832_8f63_3.jpg","is_practice_test_course":false,"image_480x270":"https://img-c.udemycdn.com/course/480x270/2360832_8f63_3.jpg","published_title":"miwebcongoogle","tracking_id":"jc8_L-J6SO6K25cAFRHl7g","headline":"Diseña tu Sitio Web con Dominio Propio y Correos Corporativos | Desde 0, Paso a paso y Sin Saber Programar","num_subscribers":7437,"caption_locales":[{"_class":"locale","locale":"es_ES","title":"Español (España)","english_title":"Spanish (Spain)"}],"avg_rating":4.7,"avg_rating_recent":4.719667,"rating":4.719667,"num_reviews":297,"is_wishlisted":false,"num_published_lectures":18,"num_published_practice_tests":0,"image_50x50":"https://img-c.udemycdn.com/course/50x50/2360832_8f63_3.jpg","image_100x100":"https://img-c.udemycdn.com/course/100x100/2360832_8f63_3.jpg","image_304x171":"https://img-c.udemycdn.com/course/304x171/2360832_8f63_3.jpg","image_750x422":"https://img-c.udemycdn.com/course/750x422/2360832_8f63_3.jpg","is_in_user_subscription":false,"locale":{"title":"Español (España)","simple_english_title":"Spanish","_class":"locale","english_title":"Spanish (Spain)","locale":"es_ES"},"has_closed_caption":true,"caption_languages":["İspanyolca [Otomatik]"],"created":"2019-05-10T02:55:50Z","instructional_level":"All Levels","instructional_level_simple":"All Levels","content_length_practice_test_questions":0,"is_user_subscribed":false,"buyable_object_type":"course","published_time":"2019-06-07T18:54:13Z","objectives_summary":["Crear el Sitio Web con Google Sites Fácil y Rápido.","Estructurar un sitio web desde cero sin tener conocimientos de programación.","Configurar tu propio dominio web."],"is_recently_published":false,"last_update_date":"2021-02-09","preview_url":"/course/2360832/preview/","learn_url":"/course/miwebcongoogle/learn/","predictive_score":null,"relevancy_score":null,"input_features":null,"lecture_search_result":null,"curriculum_lectures":[],"order_in_results":null,"curriculum_items":[],"instructor_name":null,"content_info":"1.5 total hours","content_info_short":"1.5 hours","bestseller_badge_content":null,"badges":[],"free_course_subscribe_url":"/course/subscribe/?courseId=2360832","context_info":{"category":{"title":"Design","tracking_object_type":"cat","url":"/courses/design/","id":269},"label":{"title":"Web Design","tracking_object_type":"cl","topic_channel_url":"/topic/web-design/","url":"/topic/web-design/","display_name":"Web Design","id":8320},"subcategory":null}},{"_class":"course","id":2167746,"title":"Wordpress: Crea una página web desde cero -2021 Curso básico","url":"/course/wordpress-crea-una-pagina-web-desde-cero-curso-basico/","is_paid":false,"visible_instructors":[{"_class":"user","id":20271642,"title":"Oscar Peña","name":"Oscar","display_name":"Oscar Peña","job_title":"Especialista en Marketing Digital para Empresas","image_50x50":"https://img-c.udemycdn.com/user/50x50/20271642_0387_2.jpg","image_100x100":"https://img-c.udemycdn.com/user/100x100/20271642_0387_2.jpg","initials":"OP","url":"/user/oscar-pena-4/"}],"image_125_H":"https://img-c.udemycdn.com/course/125_H/2167746_0dd6.jpg","image_240x135":"https://img-c.udemycdn.com/course/240x135/2167746_0dd6.jpg","is_practice_test_course":false,"image_480x270":"https://img-c.udemycdn.com/course/480x270/2167746_0dd6.jpg","published_title":"wordpress-crea-una-pagina-web-desde-cero-curso-basico","tracking_id":"nnqPtz1YRQ6vzMopfHcZiw","headline":"Aprende a crear tu página web usando Wordpress, la plataforma más sencilla para diseñar sitios. No necesitas programar.","num_subscribers":12314,"caption_locales":[],"avg_rating":4.0666666,"avg_rating_recent":3.985018,"rating":3.985018,"num_reviews":284,"is_wishlisted":false,"num_published_lectures":18,"num_published_practice_tests":0,"image_50x50":"https://img-c.udemycdn.com/course/50x50/2167746_0dd6.jpg","image_100x100":"https://img-c.udemycdn.com/course/100x100/2167746_0dd6.jpg","image_304x171":"https://img-c.udemycdn.com/course/304x171/2167746_0dd6.jpg","image_750x422":"https://img-c.udemycdn.com/course/750x422/2167746_0dd6.jpg","is_in_user_subscription":false,"locale":{"_class":"locale","locale":"es_MX","title":"Español (México)","english_title":"Spanish (Mexico)","simple_english_title":"Spanish"},"has_closed_caption":false,"caption_languages":[],"created":"2019-01-22T04:38:36Z","instructional_level":"Beginner Level","instructional_level_simple":"Beginner","content_length_practice_test_questions":0,"is_user_subscribed":false,"buyable_object_type":"course","published_time":"2019-01-25T00:41:34Z","objectives_summary":["Aprenderás a montar un sitio web desde cero sin necesidad de programar","Tendrás WordPress instalado en tu página web","Aprenderás a comprar tu hospedaje web y dominio (el nombre de tu página)"],"is_recently_published":false,"last_update_date":"2021-08-14","preview_url":"/course/2167746/preview/","learn_url":"/course/wordpress-crea-una-pagina-web-desde-cero-curso-basico/learn/","predictive_score":null,"relevancy_score":null,"input_features":null,"lecture_search_result":null,"curriculum_lectures":[],"order_in_results":null,"curriculum_items":[],"instructor_name":null,"content_info":"2 total hours","content_info_short":"2 hours","bestseller_badge_content":null,"badges":[],"free_course_subscribe_url":"/course/subscribe/?courseId=2167746","context_info":{"category":{"title":"Design","tracking_object_type":"cat","url":"/courses/design/","id":269},"subcategory":null,"label":{"title":"WordPress","tracking_object_type":"cl","topic_channel_url":"/topic/wordpress/","url":"/topic/wordpress/","display_name":"WordPress","id":8452}}},{"_class":"course","id":1530142,"title":"Cómo hacer un Blog GRATIS con Wordpress - CREA TÚ BLOG HOY","url":"/course/como-hacer-un-blog-gratis-wordpress-crear-blog/","is_paid":false,"visible_instructors":[{"title":"Jonathan Rengifo","name":"Jonathan","id":13637530,"image_50x50":"https://img-c.udemycdn.com/user/50x50/13637530_7de3_4.jpg","image_100x100":"https://img-c.udemycdn.com/user/100x100/13637530_7de3_4.jpg","url":"/user/jonathan-rengifo/","display_name":"Jonathan Rengifo","job_title":"Experto en Marketing y Negocios Digitales","initials":"JR","_class":"user"}],"image_125_H":"https://img-c.udemycdn.com/course/125_H/1530142_7bc8.jpg","image_240x135":"https://img-c.udemycdn.com/course/240x135/1530142_7bc8.jpg","is_practice_test_course":false,"image_480x270":"https://img-c.udemycdn.com/course/480x270/1530142_7bc8.jpg","published_title":"como-hacer-un-blog-gratis-wordpress-crear-blog","tracking_id":"dJKJP54YTWWJ1waLseTzcA","headline":"¡Wordpress!, aprender a crear un sitio web de manera gratuita con el CMS más usado del mundo.","num_subscribers":8383,"caption_locales":[{"_class":"locale","locale":"es_ES","title":"Español (España)","english_title":"Spanish (Spain)"}],"avg_rating":4.65,"avg_rating_recent":4.5565023,"rating":4.5565023,"num_reviews":279,"is_wishlisted":false,"num_published_lectures":5,"num_published_practice_tests":0,"image_50x50":"https://img-c.udemycdn.com/course/50x50/1530142_7bc8.jpg","image_100x100":"https://img-c.udemycdn.com/course/100x100/1530142_7bc8.jpg","image_304x171":"https://img-c.udemycdn.com/course/304x171/1530142_7bc8.jpg","image_750x422":"https://img-c.udemycdn.com/course/750x422/1530142_7bc8.jpg","is_in_user_subscription":false,"locale":{"title":"Español (España)","simple_english_title":"Spanish","_class":"locale","locale":"es_ES","english_title":"Spanish (Spain)"},"has_closed_caption":true,"caption_languages":["Español [automático]"],"created":"2018-01-28T21:43:44Z","instructional_level":"Beginner Level","instructional_level_simple":"Beginner","content_length_practice_test_questions":0,"is_user_subscribed":false,"buyable_object_type":"course","published_time":"2018-01-30T14:25:16Z","objectives_summary":["Crear un Sitio Web con un Blog"],"is_recently_published":false,"last_update_date":"2018-01-29","preview_url":"/course/1530142/preview/","learn_url":"/course/como-hacer-un-blog-gratis-wordpress-crear-blog/learn/","predictive_score":null,"relevancy_score":null,"input_features":null,"lecture_search_result":null,"curriculum_lectures":[],"order_in_results":null,"curriculum_items":[],"instructor_name":null,"content_info":"32 total mins","content_info_short":"32 mins","bestseller_badge_content":null,"badges":[],"free_course_subscribe_url":"/course/subscribe/?courseId=1530142","context_info":{"category":{"title":"Design","tracking_object_type":"cat","url":"/courses/design/","id":269},"subcategory":null,"label":{"title":"WordPress","tracking_object_type":"cl","topic_channel_url":"/topic/wordpress/","url":"/topic/wordpress/","display_name":"WordPress","id":8452}}},{"_class":"course","id":42211,"title":"Wordpress Desde Cero - Nivel Básico e Intermedio","url":"/course/curso-basico-de-wordpress/","is_paid":false,"visible_instructors":[{"_class":"user","id":201592,"title":"Pablo Farias Navarro","name":"Pablo","display_name":"Pablo Farias Navarro","job_title":"Certified Game Developer and Founder of ZENVA","image_50x50":"https://img-c.udemycdn.com/user/50x50/201592_beaa_5.jpg","image_100x100":"https://img-c.udemycdn.com/user/100x100/201592_beaa_5.jpg","initials":"PF","url":"/user/pablofariasnavarro/"},{"_class":"user","id":30402002,"title":"Zenva Academy","name":"Zenva","display_name":"Zenva Academy","job_title":"Build Games, Apps, Websites and VR Experiences","image_50x50":"https://img-c.udemycdn.com/user/50x50/30402002_48cf_2.jpg","image_100x100":"https://img-c.udemycdn.com/user/100x100/30402002_48cf_2.jpg","initials":"ZA","url":"/user/zenva/"}],"image_125_H":"https://img-c.udemycdn.com/course/125_H/42211_95e2_9.jpg","image_240x135":"https://img-c.udemycdn.com/course/240x135/42211_95e2_9.jpg","is_practice_test_course":false,"image_480x270":"https://img-c.udemycdn.com/course/480x270/42211_95e2_9.jpg","published_title":"curso-basico-de-wordpress","tracking_id":"xrydmABuQjmmf-cvuXSjqw","headline":"Crea tu primer sitio web con el gestor de contenidos más usado en el mundo. Todo partiendo desde cero y sin programar!","num_subscribers":12661,"caption_locales":[{"_class":"locale","locale":"es_CL","title":"Español (Chile)","english_title":"Spanish (Chile)"}],"avg_rating":3.8809524,"avg_rating_recent":3.7841082,"rating":3.7841082,"num_reviews":254,"is_wishlisted":false,"num_published_lectures":35,"num_published_practice_tests":0,"image_50x50":"https://img-c.udemycdn.com/course/50x50/42211_95e2_9.jpg","image_100x100":"https://img-c.udemycdn.com/course/100x100/42211_95e2_9.jpg","image_304x171":"https://img-c.udemycdn.com/course/304x171/42211_95e2_9.jpg","image_750x422":"https://img-c.udemycdn.com/course/750x422/42211_95e2_9.jpg","is_in_user_subscription":false,"locale":{"_class":"locale","locale":"es_CL","title":"Español (Chile)","english_title":"Spanish (Chile)","simple_english_title":"Spanish"},"has_closed_caption":true,"caption_languages":["Spanish [Auto]"],"created":"2013-02-18T12:57:05Z","instructional_level":"All Levels","instructional_level_simple":"All Levels","content_length_practice_test_questions":0,"is_user_subscribed":false,"buyable_object_type":"course","published_time":"2013-02-18T15:19:09Z","objectives_summary":["Creación de un sitio web o blog utilizando Wordpress"],"is_recently_published":false,"last_update_date":"2020-04-28","preview_url":"/course/42211/preview/","learn_url":"/course/curso-basico-de-wordpress/learn/","predictive_score":null,"relevancy_score":null,"input_features":null,"lecture_search_result":null,"curriculum_lectures":[],"order_in_results":null,"curriculum_items":[],"instructor_name":null,"content_info":"2 total hours","content_info_short":"2 hours","bestseller_badge_content":null,"badges":[],"free_course_subscribe_url":"/course/subscribe/?courseId=42211","context_info":{"category":{"title":"Design","tracking_object_type":"cat","url":"/courses/design/","id":269},"subcategory":null,"label":{"title":"WordPress","tracking_object_type":"cl","topic_channel_url":"/topic/wordpress/","url":"/topic/wordpress/","display_name":"WordPress","id":8452}}},{"_class":"course","id":2695510,"title":"Blog Yazarlığı","url":"/course/blog-yazarlg/","is_paid":false,"visible_instructors":[{"title":"Ahmet Doğru","name":"Ahmet","id":91954390,"image_50x50":"https://img-c.udemycdn.com/user/50x50/91954390_df03.jpg","image_100x100":"https://img-c.udemycdn.com/user/100x100/91954390_df03.jpg","url":"/user/ahmet-dogru-12/","display_name":"Ahmet Doğru","job_title":"Yazar, Blog yazarı, Görsel effect","initials":"AD","_class":"user"}],"image_125_H":"https://img-c.udemycdn.com/course/125_H/2695510_5371_3.jpg","image_240x135":"https://img-c.udemycdn.com/course/240x135/2695510_5371_3.jpg","is_practice_test_course":false,"image_480x270":"https://img-c.udemycdn.com/course/480x270/2695510_5371_3.jpg","published_title":"blog-yazarlg","tracking_id":"VxNU91kaQ8mBIQ-l5v0qkg","headline":"Blogger","num_subscribers":7541,"caption_locales":[],"avg_rating":4.35,"avg_rating_recent":4.294125,"rating":4.294125,"num_reviews":229,"is_wishlisted":false,"num_published_lectures":12,"num_published_practice_tests":0,"image_50x50":"https://img-c.udemycdn.com/course/50x50/2695510_5371_3.jpg","image_100x100":"https://img-c.udemycdn.com/course/100x100/2695510_5371_3.jpg","image_304x171":"https://img-c.udemycdn.com/course/304x171/2695510_5371_3.jpg","image_750x422":"https://img-c.udemycdn.com/course/750x422/2695510_5371_3.jpg","is_in_user_subscription":false,"locale":{"title":"Türkçe","simple_english_title":"Turkish","english_title":"Turkish","locale":"tr_TR","_class":"locale"},"has_closed_caption":false,"caption_languages":[],"created":"2019-12-08T13:19:40Z","instructional_level":"Beginner Level","instructional_level_simple":"Beginner","content_length_practice_test_questions":0,"is_user_subscribed":false,"buyable_object_type":"course","published_time":"2019-12-22T10:56:19Z","objectives_summary":["Blog yazarlığı","Blog yazarlığı"],"is_recently_published":false,"last_update_date":"2019-12-09","preview_url":"/course/2695510/preview/","learn_url":"/course/blog-yazarlg/learn/","predictive_score":null,"relevancy_score":null,"input_features":null,"lecture_search_result":null,"curriculum_lectures":[],"order_in_results":null,"curriculum_items":[],"instructor_name":null,"content_info":"1 total hour","content_info_short":"1 hour","bestseller_badge_content":null,"badges":[],"free_course_subscribe_url":"/course/subscribe/?courseId=2695510","context_info":{"category":{"title":"Design","tracking_object_type":"cat","url":"/courses/design/","id":269},"label":{"title":"Blogging","tracking_object_type":"cl","topic_channel_url":"/topic/blogging/","url":"/topic/blogging/","display_name":"Blogging","id":4796},"subcategory":null}},{"_class":"course","id":2844854,"title":"Crear una Página Web Desde Cero 2020","url":"/course/crear-una-pagina-web-desde-cero-2020/","is_paid":false,"visible_instructors":[{"title":"Omar Castañeda","name":"Omar","id":5319354,"image_50x50":"https://img-c.udemycdn.com/user/50x50/5319354_da80.jpg","image_100x100":"https://img-c.udemycdn.com/user/100x100/5319354_da80.jpg","url":"/user/omarcastaneda/","display_name":"Omar Castañeda","job_title":"Director Ejecutivo AskTutorial","initials":"OC","_class":"user"}],"image_125_H":"https://img-c.udemycdn.com/course/125_H/2844854_595b.jpg","image_240x135":"https://img-c.udemycdn.com/course/240x135/2844854_595b.jpg","is_practice_test_course":false,"image_480x270":"https://img-c.udemycdn.com/course/480x270/2844854_595b.jpg","published_title":"crear-una-pagina-web-desde-cero-2020","tracking_id":"vDXDvKVzS5GbaroDWbO18w","headline":"Curso creado con Wordpress y el tema mas popular del momento DIVI","num_subscribers":11478,"caption_locales":[{"_class":"locale","locale":"es_LA","title":"Español","english_title":"Spanish"}],"avg_rating":4.3,"avg_rating_recent":4.3461194,"rating":4.3461194,"num_reviews":228,"is_wishlisted":false,"num_published_lectures":27,"num_published_practice_tests":0,"image_50x50":"https://img-c.udemycdn.com/course/50x50/2844854_595b.jpg","image_100x100":"https://img-c.udemycdn.com/course/100x100/2844854_595b.jpg","image_304x171":"https://img-c.udemycdn.com/course/304x171/2844854_595b.jpg","image_750x422":"https://img-c.udemycdn.com/course/750x422/2844854_595b.jpg","is_in_user_subscription":false,"locale":{"title":"Español","simple_english_title":"Spanish","_class":"locale","english_title":"Spanish","locale":"es_LA"},"has_closed_caption":true,"caption_languages":["Spanish [Auto]"],"created":"2020-03-01T14:22:12Z","instructional_level":"All Levels","instructional_level_simple":"All Levels","content_length_practice_test_questions":0,"is_user_subscribed":false,"buyable_object_type":"course","published_time":"2020-03-03T19:46:20Z","objectives_summary":["Este curso te permitirá crear una Página Web Profesional Desde Cero sin uso de códigos o procesos difíciles de implementar. El curso de basa en uno de los métodos más utilizados a nivel mundial por cientos de diseñadores Web, en donde de manera fácil y rápida pueden crear sitios Web en cientos de estilos diferentes enfocados a cualquier tipo de empresa.","El curso emplea el tema Wordpress más popular del mundo llamado Divi. Divi es un tema multipropósito el cual mediante bloques te permite arrastrar y colocar elementos de una página Web en la posición y tamaño deseado. Incluye además cientos de plantillas prediseñadas, para ser editadas de manera instantánea, además de que cuenta con una cantidad extensa de módulos, para no solo agregar texto, video, imágenes, sino también galerías profesionales, formularios de contacto, sliders, botones prediseñados, mapas, pie de página personalizados y efectos especiales.","Este curso te dará un acceso a un panel de control en Wordpress, desde donde podrás crear nuevas páginas, crear entradas, administrar plugins y temas, al igual que personalizar cada aspecto del sitio Web de manera fácil y rápida"],"is_recently_published":false,"last_update_date":"2020-03-01","preview_url":"/course/2844854/preview/","learn_url":"/course/crear-una-pagina-web-desde-cero-2020/learn/","predictive_score":null,"relevancy_score":null,"input_features":null,"lecture_search_result":null,"curriculum_lectures":[],"order_in_results":null,"curriculum_items":[],"instructor_name":null,"content_info":"4 total hours","content_info_short":"4 hours","bestseller_badge_content":null,"badges":[],"free_course_subscribe_url":"/course/subscribe/?courseId=2844854","context_info":{"category":{"title":"Design","tracking_object_type":"cat","id":269,"url":"/courses/design/"},"label":{"title":"Web Design","tracking_object_type":"cl","topic_channel_url":"/topic/web-design/","url":"/topic/web-design/","display_name":"Web Design","id":8320},"subcategory":null}},{"_class":"course","id":1569722,"title":"Mockup interattivo di un sito web con Sketch e Invision","url":"/course/mockup-interattivo-di-un-sito-web-con-sketch-e-invision/","is_paid":false,"visible_instructors":[{"title":"Luca Pagot","name":"Luca","job_title":"Web Designer & Web Developer","image_50x50":"https://img-c.udemycdn.com/user/50x50/808961_a62d_3.jpg","image_100x100":"https://img-c.udemycdn.com/user/100x100/808961_a62d_3.jpg","url":"/user/lucajpagot/","display_name":"Luca Pagot","id":808961,"initials":"LP","_class":"user"}],"image_125_H":"https://img-c.udemycdn.com/course/125_H/1569722_9f3f.jpg","image_240x135":"https://img-c.udemycdn.com/course/240x135/1569722_9f3f.jpg","is_practice_test_course":false,"image_480x270":"https://img-c.udemycdn.com/course/480x270/1569722_9f3f.jpg","published_title":"mockup-interattivo-di-un-sito-web-con-sketch-e-invision","tracking_id":"lUPeiWjwTG6oPOBWb881rg","headline":"","num_subscribers":5830,"caption_locales":[],"avg_rating":4.25,"avg_rating_recent":4.49506,"rating":4.49506,"num_reviews":225,"is_wishlisted":false,"num_published_lectures":8,"num_published_practice_tests":0,"image_50x50":"https://img-c.udemycdn.com/course/50x50/1569722_9f3f.jpg","image_100x100":"https://img-c.udemycdn.com/course/100x100/1569722_9f3f.jpg","image_304x171":"https://img-c.udemycdn.com/course/304x171/1569722_9f3f.jpg","image_750x422":"https://img-c.udemycdn.com/course/750x422/1569722_9f3f.jpg","is_in_user_subscription":false,"locale":{"title":"Italiano","simple_english_title":"Italian","_class":"locale","locale":"it_IT","english_title":"Italian"},"has_closed_caption":false,"caption_languages":[],"created":"2018-02-25T11:26:51Z","instructional_level":"Beginner Level","instructional_level_simple":"Beginner","content_length_practice_test_questions":0,"is_user_subscribed":false,"buyable_object_type":"course","published_time":"2018-03-06T17:56:49Z","objectives_summary":["Usare le funzioni base di Sketch, creare forme, gestire ed organizzare i livelli, modificare lo stile degli elementi, capire il funzionamento base dei simboli.","Usare le funzioni base offerte dal plugin Craft by Invision per creare prototipi animati","Usare le funzioni base del portale Invision per gestire i propri progetti e condividerli"],"is_recently_published":false,"last_update_date":"2018-03-05","preview_url":"/course/1569722/preview/","learn_url":"/course/mockup-interattivo-di-un-sito-web-con-sketch-e-invision/learn/","predictive_score":null,"relevancy_score":null,"input_features":null,"lecture_search_result":null,"curriculum_lectures":[],"order_in_results":null,"curriculum_items":[],"instructor_name":null,"content_info":"1 total hour","content_info_short":"1 hour","bestseller_badge_content":null,"badges":[],"free_course_subscribe_url":"/course/subscribe/?courseId=1569722","context_info":{"category":{"title":"Design","tracking_object_type":"cat","id":269,"url":"/courses/design/"},"label":{"title":"Wireframing","tracking_object_type":"cl","topic_channel_url":"/topic/wireframing/","url":"/topic/wireframing/","display_name":"Wireframing","id":8430},"subcategory":null}},{"_class":"course","id":1442934,"title":"Shopware Template Training - Advanced","url":"/course/shopware-template-training-advanced/","is_paid":false,"visible_instructors":[{"title":"shopware AG","name":"shopware","id":29546310,"image_50x50":"https://img-c.udemycdn.com/user/50x50/29546310_26b1_4.jpg","image_100x100":"https://img-c.udemycdn.com/user/100x100/29546310_26b1_4.jpg","url":"/user/shopware-ag/","display_name":"shopware AG","job_title":"Über Shopware","initials":"SA","_class":"user"}],"image_125_H":"https://img-c.udemycdn.com/course/125_H/1442934_4472_3.jpg","image_240x135":"https://img-c.udemycdn.com/course/240x135/1442934_4472_3.jpg","is_practice_test_course":false,"image_480x270":"https://img-c.udemycdn.com/course/480x270/1442934_4472_3.jpg","published_title":"shopware-template-training-advanced","tracking_id":"RwVG7sMOTwmmqI7tznyjVg","headline":"Lerne, wie du eine Themekonfiguration erstellst","num_subscribers":5107,"caption_locales":[],"avg_rating":4.7,"avg_rating_recent":4.5272255,"rating":4.5272255,"num_reviews":223,"is_wishlisted":false,"num_published_lectures":13,"num_published_practice_tests":0,"image_50x50":"https://img-c.udemycdn.com/course/50x50/1442934_4472_3.jpg","image_100x100":"https://img-c.udemycdn.com/course/100x100/1442934_4472_3.jpg","image_304x171":"https://img-c.udemycdn.com/course/304x171/1442934_4472_3.jpg","image_750x422":"https://img-c.udemycdn.com/course/750x422/1442934_4472_3.jpg","is_in_user_subscription":false,"locale":{"title":"Deutsch","simple_english_title":"German","english_title":"German","_class":"locale","locale":"de_DE"},"has_closed_caption":false,"caption_languages":[],"created":"2017-11-22T14:03:39Z","instructional_level":"Intermediate Level","instructional_level_simple":"Intermediate","content_length_practice_test_questions":0,"is_user_subscribed":false,"buyable_object_type":"course","published_time":"2017-12-14T17:08:13Z","objectives_summary":["Du lernst, wie man eine eigene Theme-Konfiguration erstellt.","Du wirst in jQuery-Plugins eingeführt und erfährst, wie man diese erweitert.","Du lernst, wie Stateful-Plugins mit dem StateManager funktionieren."],"is_recently_published":false,"last_update_date":"2018-04-10","preview_url":"/course/1442934/preview/","learn_url":"/course/shopware-template-training-advanced/learn/","predictive_score":null,"relevancy_score":null,"input_features":null,"lecture_search_result":null,"curriculum_lectures":[],"order_in_results":null,"curriculum_items":[],"instructor_name":null,"content_info":"2.5 total hours","content_info_short":"2.5 hours","bestseller_badge_content":null,"badges":[],"free_course_subscribe_url":"/course/subscribe/?courseId=1442934","context_info":{"category":{"title":"Design","tracking_object_type":"cat","url":"/courses/design/","id":269},"label":{"title":"Shopware","tracking_object_type":"cl","topic_channel_url":"/topic/shopware/","url":"/topic/shopware/","display_name":"Shopware","id":42144},"subcategory":null}},{"_class":"course","id":1938870,"title":"Curso completo de DIVI de 0 a 100","url":"/course/curso-completo-de-divi-de-0-a-100/","is_paid":false,"visible_instructors":[{"title":"David Sáez","name":"David","job_title":"Profesor de informática","image_50x50":"https://img-c.udemycdn.com/user/50x50/635304_3d8c_3.jpg","image_100x100":"https://img-c.udemycdn.com/user/100x100/635304_3d8c_3.jpg","url":"/user/davidkaos/","display_name":"David Sáez","id":635304,"initials":"DS","_class":"user"}],"image_125_H":"https://img-c.udemycdn.com/course/125_H/1938870_7354.jpg","image_240x135":"https://img-c.udemycdn.com/course/240x135/1938870_7354.jpg","is_practice_test_course":false,"image_480x270":"https://img-c.udemycdn.com/course/480x270/1938870_7354.jpg","published_title":"curso-completo-de-divi-de-0-a-100","tracking_id":"3vWkcRNITQ-a6SmegDPnLw","headline":"Páginas web profesionales con Divi de 0 a 100","num_subscribers":8831,"caption_locales":[{"_class":"locale","locale":"es_ES","title":"Español (España)","english_title":"Spanish (Spain)"}],"avg_rating":4.7916665,"avg_rating_recent":4.752391,"rating":4.752391,"num_reviews":215,"is_wishlisted":false,"num_published_lectures":39,"num_published_practice_tests":0,"image_50x50":"https://img-c.udemycdn.com/course/50x50/1938870_7354.jpg","image_100x100":"https://img-c.udemycdn.com/course/100x100/1938870_7354.jpg","image_304x171":"https://img-c.udemycdn.com/course/304x171/1938870_7354.jpg","image_750x422":"https://img-c.udemycdn.com/course/750x422/1938870_7354.jpg","is_in_user_subscription":false,"locale":{"title":"Español (España)","simple_english_title":"Spanish","english_title":"Spanish (Spain)","locale":"es_ES","_class":"locale"},"has_closed_caption":true,"caption_languages":["Spanish [Auto]"],"created":"2018-09-29T13:32:10Z","instructional_level":"All Levels","instructional_level_simple":"All Levels","content_length_practice_test_questions":0,"is_user_subscribed":false,"buyable_object_type":"course","published_time":"2019-01-04T02:28:24Z","objectives_summary":["Aprenderás todo lo necesario para crear desde cero tu sitio con WordPress","Instalar wordpress en tu propio hosting y dominio.","Instalar Divi en tu wordpress"],"is_recently_published":false,"last_update_date":"2020-04-13","preview_url":"/course/1938870/preview/","learn_url":"/course/curso-completo-de-divi-de-0-a-100/learn/","predictive_score":null,"relevancy_score":null,"input_features":null,"lecture_search_result":null,"curriculum_lectures":[],"order_in_results":null,"curriculum_items":[],"instructor_name":null,"content_info":"9.5 total hours","content_info_short":"9.5 hours","bestseller_badge_content":null,"badges":[],"free_course_subscribe_url":"/course/subscribe/?courseId=1938870","context_info":{"category":{"title":"Design","tracking_object_type":"cat","url":"/courses/design/","id":269},"label":{"title":"Divi","tracking_object_type":"cl","topic_channel_url":"/topic/divi/","url":"/topic/divi/","display_name":"Divi","id":155970},"subcategory":null}},{"_class":"course","id":3294068,"title":"Figma tutorial - Diseña una increíble página web con Figma","url":"/course/disena-una-increible-pagina-web-con-figma/","is_paid":false,"visible_instructors":[{"title":"Diego Velazquez","name":"Diego","id":40557036,"image_50x50":"https://img-c.udemycdn.com/user/50x50/40557036_dab0_3.jpg","image_100x100":"https://img-c.udemycdn.com/user/100x100/40557036_dab0_3.jpg","url":"/user/diego-velazquez-9/","display_name":"Diego Velazquez","job_title":"Front End Developer & UI / UX Designer","initials":"DV","_class":"user"}],"image_125_H":"https://img-c.udemycdn.com/course/125_H/3294068_93e5_2.jpg","image_240x135":"https://img-c.udemycdn.com/course/240x135/3294068_93e5_2.jpg","is_practice_test_course":false,"image_480x270":"https://img-c.udemycdn.com/course/480x270/3294068_93e5_2.jpg","published_title":"disena-una-increible-pagina-web-con-figma","tracking_id":"DIjiXebZQn69H4qiJWy5gg","headline":"Aprende a diseñar una página web atractiva con Figma","num_subscribers":6709,"caption_locales":[{"_class":"locale","locale":"es_MX","title":"Español (México)","english_title":"Spanish (Mexico)"}],"avg_rating":4.419355,"avg_rating_recent":4.4364605,"rating":4.4364605,"num_reviews":211,"is_wishlisted":false,"num_published_lectures":6,"num_published_practice_tests":0,"image_50x50":"https://img-c.udemycdn.com/course/50x50/3294068_93e5_2.jpg","image_100x100":"https://img-c.udemycdn.com/course/100x100/3294068_93e5_2.jpg","image_304x171":"https://img-c.udemycdn.com/course/304x171/3294068_93e5_2.jpg","image_750x422":"https://img-c.udemycdn.com/course/750x422/3294068_93e5_2.jpg","is_in_user_subscription":false,"locale":{"title":"Español (México)","simple_english_title":"Spanish","_class":"locale","locale":"es_MX","english_title":"Spanish (Mexico)"},"has_closed_caption":true,"caption_languages":["Español [automático]"],"created":"2020-07-03T04:24:57Z","instructional_level":"Beginner Level","instructional_level_simple":"Beginner","content_length_practice_test_questions":0,"is_user_subscribed":false,"buyable_object_type":"course","published_time":"2020-07-07T00:29:27Z","objectives_summary":["Crear una página web con Figma","Diseñar una página web con Figma","Aprender a utilizar Figma"],"is_recently_published":false,"last_update_date":"2021-03-13","preview_url":"/course/3294068/preview/","learn_url":"/course/disena-una-increible-pagina-web-con-figma/learn/","predictive_score":null,"relevancy_score":null,"input_features":null,"lecture_search_result":null,"curriculum_lectures":[],"order_in_results":null,"curriculum_items":[],"instructor_name":null,"content_info":"1.5 total hours","content_info_short":"1.5 hours","bestseller_badge_content":null,"badges":[],"free_course_subscribe_url":"/course/subscribe/?courseId=3294068","context_info":{"category":{"title":"Design","tracking_object_type":"cat","id":269,"url":"/courses/design/"},"label":{"title":"Web Design","tracking_object_type":"cl","topic_channel_url":"/topic/web-design/","url":"/topic/web-design/","display_name":"Web Design","id":8320},"subcategory":null}},{"_class":"course","id":2510292,"title":"من الآول الى الآخر تعلم آمازون كيندل KDP","url":"/course/mercherworld/","is_paid":false,"visible_instructors":[{"title":"Mohamed Hadji","name":"Mohamed","job_title":"Entrepreneur","image_50x50":"https://img-c.udemycdn.com/user/50x50/33125684_7e73_2.jpg","image_100x100":"https://img-c.udemycdn.com/user/100x100/33125684_7e73_2.jpg","url":"/user/mohamed-hadji-2/","display_name":"Mohamed Hadji","id":33125684,"initials":"MH","_class":"user"}],"image_125_H":"https://img-c.udemycdn.com/course/125_H/2510292_b6e6_2.jpg","image_240x135":"https://img-c.udemycdn.com/course/240x135/2510292_b6e6_2.jpg","is_practice_test_course":false,"image_480x270":"https://img-c.udemycdn.com/course/480x270/2510292_b6e6_2.jpg","published_title":"mercherworld","tracking_id":"Q6DostSzQlOO4vbDSncefg","headline":"انشر أول كتاب لك على أمازون","num_subscribers":3758,"caption_locales":[],"avg_rating":4.5,"avg_rating_recent":4.3716383,"rating":4.3716383,"num_reviews":205,"is_wishlisted":false,"num_published_lectures":8,"num_published_practice_tests":0,"image_50x50":"https://img-c.udemycdn.com/course/50x50/2510292_b6e6_2.jpg","image_100x100":"https://img-c.udemycdn.com/course/100x100/2510292_b6e6_2.jpg","image_304x171":"https://img-c.udemycdn.com/course/304x171/2510292_b6e6_2.jpg","image_750x422":"https://img-c.udemycdn.com/course/750x422/2510292_b6e6_2.jpg","is_in_user_subscription":false,"locale":{"title":"العربية","simple_english_title":"Arabic","_class":"locale","locale":"ar_AR","english_title":"Arabic"},"has_closed_caption":false,"caption_languages":[],"created":"2019-08-15T06:48:57Z","instructional_level":"Beginner Level","instructional_level_simple":"Beginner","content_length_practice_test_questions":0,"is_user_subscribed":false,"buyable_object_type":"course","published_time":"2020-01-14T01:01:10Z","objectives_summary":["تصميم الكتب بدون محتوى وبيعها على امازون"],"is_recently_published":false,"last_update_date":"2020-01-11","preview_url":"/course/2510292/preview/","learn_url":"/course/mercherworld/learn/","predictive_score":null,"relevancy_score":null,"input_features":null,"lecture_search_result":null,"curriculum_lectures":[],"order_in_results":null,"curriculum_items":[],"instructor_name":null,"content_info":"1.5 total hours","content_info_short":"1.5 hours","bestseller_badge_content":null,"badges":[],"free_course_subscribe_url":"/course/subscribe/?courseId=2510292","context_info":{"category":{"title":"Design","tracking_object_type":"cat","id":269,"url":"/courses/design/"},"label":{"title":"Amazon Kindle Direct Publishing (KDP)","tracking_object_type":"cl","topic_channel_url":"/topic/amazon-kindle/","url":"/topic/amazon-kindle/","display_name":"Amazon Kindle Direct Publishing (KDP)","id":4456},"subcategory":null}},{"_class":"course","id":2065617,"title":"Como crear una web inmobiliaria con WordPress, WPL y Divi","url":"/course/como-crear-una-web-inmobiliaria-con-wordpress-wpl-y-divi/","is_paid":false,"visible_instructors":[{"title":"Alan Fox","name":"Alan","job_title":"Diseñador de sitios web","image_50x50":"https://img-c.udemycdn.com/user/50x50/56862482_8016.jpg","image_100x100":"https://img-c.udemycdn.com/user/100x100/56862482_8016.jpg","url":"/user/alan-660/","display_name":"Alan Fox","id":56862482,"initials":"AF","_class":"user"}],"image_125_H":"https://img-c.udemycdn.com/course/125_H/2065617_d4fe_2.jpg","image_240x135":"https://img-c.udemycdn.com/course/240x135/2065617_d4fe_2.jpg","is_practice_test_course":false,"image_480x270":"https://img-c.udemycdn.com/course/480x270/2065617_d4fe_2.jpg","published_title":"como-crear-una-web-inmobiliaria-con-wordpress-wpl-y-divi","tracking_id":"ngKI9U4QTfGNv_b7a76pmA","headline":"En esta serie de videos te enseña a crear una web inmobiliaria con WordPress, WPL y Divi","num_subscribers":8642,"caption_locales":[{"_class":"locale","locale":"es_ES","title":"Español (España)","english_title":"Spanish (Spain)"}],"avg_rating":4.4,"avg_rating_recent":4.443356,"rating":4.443356,"num_reviews":192,"is_wishlisted":false,"num_published_lectures":23,"num_published_practice_tests":0,"image_50x50":"https://img-c.udemycdn.com/course/50x50/2065617_d4fe_2.jpg","image_100x100":"https://img-c.udemycdn.com/course/100x100/2065617_d4fe_2.jpg","image_304x171":"https://img-c.udemycdn.com/course/304x171/2065617_d4fe_2.jpg","image_750x422":"https://img-c.udemycdn.com/course/750x422/2065617_d4fe_2.jpg","is_in_user_subscription":false,"locale":{"title":"Español (España)","simple_english_title":"Spanish","_class":"locale","locale":"es_ES","english_title":"Spanish (Spain)"},"has_closed_caption":true,"caption_languages":["Spanish [Auto]"],"created":"2018-12-03T19:23:40Z","instructional_level":"Beginner Level","instructional_level_simple":"Beginner","content_length_practice_test_questions":0,"is_user_subscribed":false,"buyable_object_type":"course","published_time":"2019-01-08T15:04:12Z","objectives_summary":["Crear una página web para inmobiliaria personalizada"],"is_recently_published":false,"last_update_date":"2021-09-12","preview_url":"/course/2065617/preview/","learn_url":"/course/como-crear-una-web-inmobiliaria-con-wordpress-wpl-y-divi/learn/","predictive_score":null,"relevancy_score":null,"input_features":null,"lecture_search_result":null,"curriculum_lectures":[],"order_in_results":null,"curriculum_items":[],"instructor_name":null,"content_info":"1.5 total hours","content_info_short":"1.5 hours","bestseller_badge_content":null,"badges":[],"free_course_subscribe_url":"/course/subscribe/?courseId=2065617","context_info":{"category":{"title":"Design","tracking_object_type":"cat","url":"/courses/design/","id":269},"subcategory":null,"label":{"title":"Divi","tracking_object_type":"cl","topic_channel_url":"/topic/divi/","url":"/topic/divi/","display_name":"Divi","id":155970}}},{"_class":"course","id":1959640,"title":"Diseña tu portafolio web con WordPress y Divi","url":"/course/disena-tu-portafolio-web-con-wordpress-y-divi/","is_paid":false,"visible_instructors":[{"title":"Oscar Viedma","name":"Oscar","id":22513394,"image_50x50":"https://img-c.udemycdn.com/user/50x50/22513394_c50b_2.jpg","image_100x100":"https://img-c.udemycdn.com/user/100x100/22513394_c50b_2.jpg","url":"/user/oscar-viedma/","display_name":"Oscar Viedma","job_title":"Diseñador web freelance","initials":"OV","_class":"user"}],"image_125_H":"https://img-c.udemycdn.com/course/125_H/1959640_e0db_2.jpg","image_240x135":"https://img-c.udemycdn.com/course/240x135/1959640_e0db_2.jpg","is_practice_test_course":false,"image_480x270":"https://img-c.udemycdn.com/course/480x270/1959640_e0db_2.jpg","published_title":"disena-tu-portafolio-web-con-wordpress-y-divi","tracking_id":"ExHaZH39QG6DX7Vj8mVG2g","headline":"Aprende a diseñar un sitio web profesional sin habilidades de codificación con WordPress y Divi","num_subscribers":10971,"caption_locales":[{"_class":"locale","locale":"es_ES","title":"Español (España)","english_title":"Spanish (Spain)"}],"avg_rating":4.5,"avg_rating_recent":4.8010907,"rating":4.8010907,"num_reviews":186,"is_wishlisted":false,"num_published_lectures":35,"num_published_practice_tests":0,"image_50x50":"https://img-c.udemycdn.com/course/50x50/1959640_e0db_2.jpg","image_100x100":"https://img-c.udemycdn.com/course/100x100/1959640_e0db_2.jpg","image_304x171":"https://img-c.udemycdn.com/course/304x171/1959640_e0db_2.jpg","image_750x422":"https://img-c.udemycdn.com/course/750x422/1959640_e0db_2.jpg","is_in_user_subscription":false,"locale":{"title":"Español (España)","simple_english_title":"Spanish","english_title":"Spanish (Spain)","_class":"locale","locale":"es_ES"},"has_closed_caption":true,"caption_languages":["Español [automático]"],"created":"2018-10-11T03:32:00Z","instructional_level":"Beginner Level","instructional_level_simple":"Beginner","content_length_practice_test_questions":0,"is_user_subscribed":false,"buyable_object_type":"course","published_time":"2018-10-20T18:25:35Z","objectives_summary":["Al finalizar el curso tendrás un portafolio web totalmente funcional y en línea.","Tendrás un sitio web profesional totalmente responsive (adaptable a móviles).","Obtendrás los conocimientos necesarios para realizar sitios web únicos, personales y para clientes."],"is_recently_published":false,"last_update_date":"2019-02-06","preview_url":"/course/1959640/preview/","learn_url":"/course/disena-tu-portafolio-web-con-wordpress-y-divi/learn/","predictive_score":null,"relevancy_score":null,"input_features":null,"lecture_search_result":null,"curriculum_lectures":[],"order_in_results":null,"curriculum_items":[],"instructor_name":null,"content_info":"4 total hours","content_info_short":"4 hours","bestseller_badge_content":null,"badges":[],"free_course_subscribe_url":"/course/subscribe/?courseId=1959640","context_info":{"category":{"title":"Design","tracking_object_type":"cat","url":"/courses/design/","id":269},"subcategory":null,"label":{"title":"Divi","tracking_object_type":"cl","topic_channel_url":"/topic/divi/","url":"/topic/divi/","display_name":"Divi","id":155970}}},{"_class":"course","id":1975706,"title":"WordPress + Brizy + Canva: Conviértete en diseñador web!","url":"/course/curso-brizy/","is_paid":false,"visible_instructors":[{"_class":"user","id":53341636,"title":"Fabián Karaben","name":"Fabián","display_name":"Fabián Karaben","job_title":"Administrador de Sistemas y Desarrollador Web","image_50x50":"https://img-c.udemycdn.com/user/50x50/53341636_803a.jpg","image_100x100":"https://img-c.udemycdn.com/user/100x100/53341636_803a.jpg","initials":"FK","url":"/user/fabian-karaben/"}],"image_125_H":"https://img-c.udemycdn.com/course/125_H/1975706_3a8c.jpg","image_240x135":"https://img-c.udemycdn.com/course/240x135/1975706_3a8c.jpg","is_practice_test_course":false,"image_480x270":"https://img-c.udemycdn.com/course/480x270/1975706_3a8c.jpg","published_title":"curso-brizy","tracking_id":"nlLMmjVbSkCS_uUmPZf11Q","headline":"Herramientas modernas como Brizy hacen que convertirse en Diseñador web en poco tiempo sea posible.","num_subscribers":10278,"caption_locales":[{"_class":"locale","locale":"es_LA","title":"Español","english_title":"Spanish"}],"avg_rating":4.4,"avg_rating_recent":4.4857483,"rating":4.4857483,"num_reviews":176,"is_wishlisted":false,"num_published_lectures":70,"num_published_practice_tests":0,"image_50x50":"https://img-c.udemycdn.com/course/50x50/1975706_3a8c.jpg","image_100x100":"https://img-c.udemycdn.com/course/100x100/1975706_3a8c.jpg","image_304x171":"https://img-c.udemycdn.com/course/304x171/1975706_3a8c.jpg","image_750x422":"https://img-c.udemycdn.com/course/750x422/1975706_3a8c.jpg","is_in_user_subscription":false,"locale":{"_class":"locale","locale":"es_LA","title":"Español","english_title":"Spanish","simple_english_title":"Spanish"},"has_closed_caption":true,"caption_languages":["Spanish [Auto]"],"created":"2018-10-18T21:40:35Z","instructional_level":"All Levels","instructional_level_simple":"All Levels","content_length_practice_test_questions":0,"is_user_subscribed":false,"buyable_object_type":"course","published_time":"2018-11-19T16:24:32Z","objectives_summary":["Aprenderás WordPress y diseño de páginas web desde cero.","Aprenderás a utilizar Brizy para crear diseños increíbles en WordPress.","Aprenderás conceptos relacionados a los sitios web como \"Web hosting\" o \"Dominio web\", y cómo utilizarlos."],"is_recently_published":false,"last_update_date":"2019-02-06","preview_url":"/course/1975706/preview/","learn_url":"/course/curso-brizy/learn/","predictive_score":null,"relevancy_score":null,"input_features":null,"lecture_search_result":null,"curriculum_lectures":[],"order_in_results":null,"curriculum_items":[],"instructor_name":null,"content_info":"6.5 total hours","content_info_short":"6.5 hours","bestseller_badge_content":null,"badges":[],"free_course_subscribe_url":"/course/subscribe/?courseId=1975706","context_info":{"category":{"title":"Design","tracking_object_type":"cat","url":"/courses/design/","id":269},"label":{"title":"WordPress","tracking_object_type":"cl","topic_channel_url":"/topic/wordpress/","url":"/topic/wordpress/","display_name":"WordPress","id":8452},"subcategory":null}}],"remaining_item_count":69,"url":"/api-2.0/discovery-units/all_courses/?apply_filters=True&fft=&fl=scat&gl_tracking_id=None&is_content_rankable=False&ref_tracking_id=qSZnKpl5SO2ezNlICGIuOA&sos=ps&subcategory_id=6","type":"all_courses","recommendation_params":{"fft":"","subcategory_id":6,"ref_tracking_id":"qSZnKpl5SO2ezNlICGIuOA","sos":"ps","fl":"scat","member_of":null,"gl_tracking_id":"None","is_content_rankable":false,"u":null,"apply_filters":true,"source_object_count":null},"url_title":null,"score":0.0,"available_filters":{},"aggregations":[{"title":"Subcategory","key":"subcategory","options":[{"title":"Web Design","key":"subcategory","count":1221,"value":"Web Design"}],"id":"subcategory"},{"title":"Level","open":true,"key":"instructional_level","options":[{"title":"Beginner","key":"instructional_level","count":572,"value":"beginner"},{"title":"All Levels","key":"instructional_level","count":521,"value":"all"},{"title":"Intermediate","key":"instructional_level","count":117,"value":"intermediate"},{"title":"Expert","key":"instructional_level","count":11,"value":"expert"}],"all_title":"All Levels","id":"instructional_level"},{"title":"Language","all_title":"All Languages","key":"language","options":[{"title":"English","key":"lang","count":612,"value":"en"},{"title":"Español","key":"lang","count":183,"value":"es"},{"title":"日本語","key":"lang","count":91,"value":"ja"},{"title":"Português","key":"lang","count":58,"value":"pt"},{"title":"Türkçe","key":"lang","count":47,"value":"tr"},{"title":"Deutsch","key":"lang","count":36,"value":"de"},{"title":"العربية","key":"lang","count":31,"value":"ar"},{"title":"Русский","key":"lang","count":30,"value":"ru"},{"title":"Italiano","key":"lang","count":27,"value":"it"},{"title":"Français","key":"lang","count":21,"value":"fr"},{"title":"हिन्दी","key":"lang","count":18,"value":"hi"},{"title":"Polski","key":"lang","count":15,"value":"pl"},{"title":"中文","key":"lang","count":11,"value":"zh"},{"title":"Nederlands","key":"lang","count":9,"value":"nl"},{"title":"اردو","key":"lang","count":9,"value":"ur"},{"title":"한국어","key":"lang","count":5,"value":"ko"},{"title":"தமிழ்","key":"lang","count":4,"value":"ta"},{"title":"Bahasa Indonesia","key":"lang","count":3,"value":"id"},{"title":"Malayāḷam","key":"lang","count":2,"value":"ml"},{"title":"मराठी","key":"lang","count":2,"value":"mr"},{"title":"Română","key":"lang","count":2,"value":"ro"},{"title":"Telugu","key":"lang","count":2,"value":"te"},{"title":"Ελληνικά","key":"lang","count":1,"value":"el"},{"title":"فارسی","key":"lang","count":1,"value":"fa"},{"title":"Magyar","key":"lang","count":1,"value":"hu"}],"id":"language"},{"title":"Price","open":true,"key":"price","options":[{"title":"Paid","key":"price","count":988,"value":"price-paid"},{"title":"Free","key":"price","count":233,"value":"price-free"}],"all_title":"All Prices","id":"price"},{"title":"Features","key":"features","options":[{"title":"Subtitles","is_feature":true,"count":793,"key":"has_closed_caption","value":"true"},{"title":"Quizzes","is_feature":true,"count":156,"key":"has_simple_quiz","value":"true"},{"title":"Coding Exercises","is_feature":true,"count":7,"key":"has_coding_exercises","value":"true"},{"title":"Practice Tests","is_feature":true,"count":16,"key":"has_practice_test","value":"true"}],"id":"features"},{"title":"Ratings","all_title":"Ratings","key":"ratings","options":[{"title":"4.5 & up","key":"ratings","count":425,"value":"4.5"},{"title":"4.0 & up","key":"ratings","count":855,"value":"4.0"},{"title":"3.5 & up","key":"ratings","count":1037,"value":"3.5"},{"title":"3.0 & up","key":"ratings","count":1086,"value":"3.0"}],"id":"ratings"},{"title":"Video Duration","all_title":"","key":"duration","options":[{"title":"0-1 Hour","key":"duration","count":100,"value":"extraShort"},{"title":"1-3 Hours","key":"duration","count":523,"value":"short"},{"title":"3-6 Hours","key":"duration","count":313,"value":"medium"},{"title":"6-17 Hours","key":"duration","count":227,"value":"long"},{"title":"17+ Hours","key":"duration","count":58,"value":"extraLong"}],"id":"duration"},{"title":"Subtitles","key":"closed_captions","options":[{"title":"English","key":"closed_captions","count":566,"value":"en"},{"title":"Español","key":"closed_captions","count":185,"value":"es"},{"title":"Português","key":"closed_captions","count":51,"value":"pt"},{"title":"Polski","key":"closed_captions","count":16,"value":"pl"},{"title":"Italiano","key":"closed_captions","count":13,"value":"it"},{"title":"Bahasa Indonesia","key":"closed_captions","count":8,"value":"id"},{"title":"Français","key":"closed_captions","count":6,"value":"fr"},{"title":"日本語","key":"closed_captions","count":6,"value":"ja"},{"title":"Română","key":"closed_captions","count":5,"value":"ro"},{"title":"ภาษาไทย","key":"closed_captions","count":4,"value":"th"}],"id":"closed_captions"}],"course_labels":[{"_class":"course_label","id":8452,"title":"WordPress","display_name":"WordPress","doc_count":348},{"_class":"course_label","id":8320,"title":"Web Design","display_name":"Web Design","doc_count":243},{"_class":"course_label","id":5306,"title":"CSS","display_name":"CSS","doc_count":83},{"_class":"course_label","id":6148,"title":"HTML","display_name":"HTML","doc_count":52},{"_class":"course_label","id":4402,"title":"Photoshop","display_name":"Photoshop","doc_count":51},{"_class":"course_label","id":4820,"title":"Bootstrap","display_name":"Bootstrap","doc_count":36},{"_class":"course_label","id":9286,"title":"HTML5","display_name":"HTML5","doc_count":34},{"_class":"course_label","id":7506,"title":"Responsive Design","display_name":"Responsive Design","doc_count":25},{"_class":"course_label","id":155970,"title":"Divi","display_name":"Divi","doc_count":24},{"_class":"course_label","id":4796,"title":"Blogging","display_name":"Blogging","doc_count":23},{"_class":"course_label","id":8322,"title":"Web Development","display_name":"Web Development","doc_count":23},{"_class":"course_label","id":13612,"title":"Web Design Business","display_name":"Web Design Business","doc_count":20},{"_class":"course_label","id":10174,"title":"WordPress Plugins","display_name":"WordPress Plugins","doc_count":18},{"_class":"course_label","id":6368,"title":"JavaScript","display_name":"JavaScript","doc_count":17},{"_class":"course_label","id":38988,"title":"Elementor","display_name":"Elementor","doc_count":17},{"_class":"course_label","id":4382,"title":"Dreamweaver","display_name":"Dreamweaver","doc_count":15},{"_class":"course_label","id":5386,"title":"User Experience Design","display_name":"User Experience Design","doc_count":15},{"_class":"course_label","id":12290,"title":"Adobe XD","display_name":"Adobe XD","doc_count":15},{"_class":"course_label","id":33474,"title":"WordPress Themes","display_name":"WordPress Themes","doc_count":15},{"_class":"course_label","id":46554,"title":"Figma","display_name":"Figma","doc_count":15},{"_class":"course_label","id":6484,"title":"Landing Page Optimization","display_name":"Landing Page Optimization","doc_count":14},{"_class":"course_label","id":5884,"title":"Front End Web Development","display_name":"Front End Web Development","doc_count":13},{"_class":"course_label","id":8172,"title":"User Interface","display_name":"User Interface","doc_count":13},{"_class":"course_label","id":10026,"title":"CSS Animations","display_name":"CSS Animations","doc_count":11},{"_class":"course_label","id":6396,"title":"Joomla","display_name":"Joomla","doc_count":10}],"sort_options":{"options":[{"key":"highest-rated","label":"Highest Rated","url":"/api-2.0/discovery-units/all_courses/?closed_captions=&currency=aud&duration=&fl=scat&instructional_level=&lang=&locale=en_US&navigation_locale=en_US&p=72&page_size=16&price=&skip_price=true&sos=ps&source_page=subcategory_page&subcategory=&subcategory_id=6&subs_filter_type=&sort=highest-rated"},{"key":"newest","label":"Newest","url":"/api-2.0/discovery-units/all_courses/?closed_captions=&currency=aud&duration=&fl=scat&instructional_level=&lang=&locale=en_US&navigation_locale=en_US&p=72&page_size=16&price=&skip_price=true&sos=ps&source_page=subcategory_page&subcategory=&subcategory_id=6&subs_filter_type=&sort=newest"}],"current_sort_option":{"key":"popularity","label":"Popularity","url":"/api-2.0/discovery-units/all_courses/?closed_captions=&currency=aud&duration=&fl=scat&instructional_level=&lang=&locale=en_US&navigation_locale=en_US&p=72&page_size=16&price=&skip_price=true&sos=ps&source_page=subcategory_page&subcategory=&subcategory_id=6&subs_filter_type=&sort=popularity"}},"pagination":{"next":{"label":"Next","selected":false,"url":"/api-2.0/discovery-units/all_courses/?closed_captions=&currency=aud&duration=&fl=scat&instructional_level=&lang=&locale=en_US&navigation_locale=en_US&p=73&page_size=16&price=&skip_price=true&sos=ps&source_page=subcategory_page&subcategory=&subcategory_id=6&subs_filter_type="},"current_page":72,"total_page":77,"total_item_count":1221,"pages":[{"label":70,"selected":false,"url":"/api-2.0/discovery-units/all_courses/?closed_captions=&currency=aud&duration=&fl=scat&instructional_level=&lang=&locale=en_US&navigation_locale=en_US&p=70&page_size=16&price=&skip_price=true&sos=ps&source_page=subcategory_page&subcategory=&subcategory_id=6&subs_filter_type="},{"label":71,"selected":false,"url":"/api-2.0/discovery-units/all_courses/?closed_captions=&currency=aud&duration=&fl=scat&instructional_level=&lang=&locale=en_US&navigation_locale=en_US&p=71&page_size=16&price=&skip_price=true&sos=ps&source_page=subcategory_page&subcategory=&subcategory_id=6&subs_filter_type="},{"label":72,"selected":true,"url":"/api-2.0/discovery-units/all_courses/?closed_captions=&currency=aud&duration=&fl=scat&instructional_level=&lang=&locale=en_US&navigation_locale=en_US&p=72&page_size=16&price=&skip_price=true&sos=ps&source_page=subcategory_page&subcategory=&subcategory_id=6&subs_filter_type="},{"label":73,"selected":false,"url":"/api-2.0/discovery-units/all_courses/?closed_captions=&currency=aud&duration=&fl=scat&instructional_level=&lang=&locale=en_US&navigation_locale=en_US&p=73&page_size=16&price=&skip_price=true&sos=ps&source_page=subcategory_page&subcategory=&subcategory_id=6&subs_filter_type="},{"label":74,"selected":false,"url":"/api-2.0/discovery-units/all_courses/?closed_captions=&currency=aud&duration=&fl=scat&instructional_level=&lang=&locale=en_US&navigation_locale=en_US&p=74&page_size=16&price=&skip_price=true&sos=ps&source_page=subcategory_page&subcategory=&subcategory_id=6&subs_filter_type="}],"previous":{"label":"Previous","selected":false,"url":"/api-2.0/discovery-units/all_courses/?closed_captions=&currency=aud&duration=&fl=scat&instructional_level=&lang=&locale=en_US&navigation_locale=en_US&p=71&page_size=16&price=&skip_price=true&sos=ps&source_page=subcategory_page&subcategory=&subcategory_id=6&subs_filter_type="}},"view_type":"default","member_of":null,"tracking_id":"qSZnKpl5SO2ezNlICGIuOA","has_courses_in_ufb":false,"description":"","subcategory_slug":""}}